setup.py
Flask_Api_Awesomesauce.egg-info/PKG-INFO
Flask_Api_Awesomesauce.egg-info/SOURCES.txt
Flask_Api_Awesomesauce.egg-info/dependency_links.txt
Flask_Api_Awesomesauce.egg-info/requires.txt
Flask_Api_Awesomesauce.egg-info/top_level.txt
flask_api_awesomesauce/__init__.py
flask_api_awesomesauce/api_decorators.py
flask_api_awesomesauce/exceptions.py
flask_api_awesomesauce/utilities.py
flask_api_awesomesauce/tests/__init__.py
flask_api_awesomesauce/tests/test_api_decorators.py