Metadata-Version: 1.1
Name: Flask-Api-Awesomesauce
Version: 0.1
Summary: Flask Api Awesomesauce!
Home-page: https://github.com/eikonomega/flask-api-awesomesauce
Author: Mike Dunn
Author-email: mike@eikonomega.com
License: MIT
Platform: UNKNOWN
Classifier: Intended Audience :: Developers
Classifier: License :: OSI Approved :: MIT License
Classifier: Operating System :: OS Independent
Classifier: Programming Language :: Python
Classifier: Topic :: Software Development :: Libraries :: Python Modules
